pyfujitseu/__init__.py
pyfujitseu/api.py
pyfujitseu/splitAC.py
pyfujitseu-0.9.1.dist-info/LICENSE
pyfujitseu-0.9.1.dist-info/METADATA
pyfujitseu-0.9.1.dist-info/WHEEL
pyfujitseu-0.9.1.dist-info/top_level.txt
pyfujitseu-0.9.1.dist-info/RECORD
