Metadata-Version: 2.1
Name: pyfujitseu
Version: 0.9.1
Summary: Python library to control Fujitsu General Airconditioners on AylaNetworks IoT platform
Home-page: https://github.com/xerxes87/pyfujitseu
Author: Mehdi Modarressi, philwilldo
Author-email: Luckposht@gmail.com, xerxes@polizisten-duzer.de
Maintainer: @xerxes87
License: UNKNOWN
Platform: UNKNOWN
Classifier: Programming Language :: Python :: 3
Classifier: License :: OSI Approved :: MIT License
Classifier: Operating System :: OS Independent
Requires-Dist: requests
Requires-Dist: certifi
Requires-Dist: chardet
Requires-Dist: idna
Requires-Dist: urllib3
